dlr_sc_quapps-1.0.dist-info/licenses/LICENSE
quapps/__init__.py
quapps/arbitrary_ising/__init__.py
quapps/arbitrary_ising/ising_instance.py
quapps/arbitrary_ising/ising_objective.py
quapps/arbitrary_ising/test_ising_instance.py
quapps/arbitrary_ising/test_ising_objective.py
quapps/flight_gate_assignment/__init__.py
quapps/flight_gate_assignment/fga_constrained_objective.py
quapps/flight_gate_assignment/fga_instance.py
quapps/flight_gate_assignment/fga_objective_terms.py
quapps/flight_gate_assignment/fga_utils_classical_solving.py
quapps/flight_gate_assignment/test_fga_classical_solving.py
quapps/flight_gate_assignment/test_fga_constrained_objective.py
quapps/flight_gate_assignment/test_fga_instance.py
quapps/flight_gate_assignment/test_fga_objective_terms.py
quapps/graph_partitioning/__init__.py
quapps/graph_partitioning/gp_constrained_objective.py
quapps/graph_partitioning/gp_instance.py
quapps/graph_partitioning/test_gp_classical_solving.py
quapps/graph_partitioning/test_gp_constrained_objective.py
quapps/graph_partitioning/test_gp_instance.py
quapps/knapsack/__init__.py
quapps/knapsack/knapsack_constrained_objective.py
quapps/knapsack/knapsack_instance.py
quapps/knapsack/test_knapsack_classical_solving.py
quapps/knapsack/test_knapsack_constrained_objective.py
quapps/knapsack/test_knapsack_instance.py
quapps/max_colorable_subgraph/__init__.py
quapps/max_colorable_subgraph/mcs_constrained_objective.py
quapps/max_colorable_subgraph/mcs_instance.py
quapps/max_colorable_subgraph/mcs_objective_terms.py
quapps/max_colorable_subgraph/test_mcs_classical_solving.py
quapps/max_colorable_subgraph/test_mcs_constrained_objective.py
quapps/max_colorable_subgraph/test_mcs_instance.py
quapps/max_colorable_subgraph/test_mcs_objective_terms.py
quapps/max_cut/__init__.py
quapps/max_cut/max_cut_constrained_objective.py
quapps/max_cut/max_cut_instance.py
quapps/max_cut/max_cut_objective.py
quapps/max_cut/max_cut_objective_terms.py
quapps/max_cut/max_cut_scip_model.py
quapps/max_cut/test_max_cut_classical_solving.py
dlr_sc_quapps-1.0.dist-info/METADATA
dlr_sc_quapps-1.0.dist-info/WHEEL
dlr_sc_quapps-1.0.dist-info/top_level.txt
dlr_sc_quapps-1.0.dist-info/RECORD
