Metadata-Version: 2.4
Name: dlr-sc-quapps
Version: 1.0
Summary: This is a software package containing a collection of exemplary application implementations based on ``quark``.
Author-email: DLR-SC <qc-software@dlr.de>
License-Expression: Apache-2.0
Project-URL: Homepage, https://gitlab.com/quantum-computing-software/quapps/
Project-URL: Documentation, https://quantum-computing-software.gitlab.io/quapps/
Keywords: Combinatorial Optimization,QUBO,Ising Problem,Quantum Computing,Quantum Annealing
Classifier: Programming Language :: Python :: 3
Classifier: Operating System :: OS Independent
Requires-Python: >=3.11
License-File: LICENSE
Requires-Dist: pytest
Requires-Dist: numpy
Requires-Dist: networkx
Requires-Dist: sympy
Requires-Dist: dlr-sc-quark==1.2
Dynamic: license-file
